LICENSE
MANIFEST.in
README.md
setup.py
aio_nameko_proxy/__init__.py
aio_nameko_proxy/constants.py
aio_nameko_proxy/excs.py
aio_nameko_proxy/pool.py
aio_nameko_proxy/proxies.py
aio_nameko_proxy.egg-info/PKG-INFO
aio_nameko_proxy.egg-info/SOURCES.txt
aio_nameko_proxy.egg-info/dependency_links.txt
aio_nameko_proxy.egg-info/requires.txt
aio_nameko_proxy.egg-info/top_level.txt
aio_nameko_proxy/wrappers/__init__.py
aio_nameko_proxy/wrappers/sanic.py