Metadata-Version: 2.1
Name: aio-nameko-proxy
Version: 1.0.0
Summary: A standalone nameko rpc proxy for asyncio and a wrapper for using nameko rpc proxy with Sanic. 
Home-page: https://github.com/laiyongtao/aio_nameko_proxy
Author: laiyongtao
Author-email: laiyongtao6908@163.com
License: Apache License, Version 2.0
Keywords: nameko,sanic,asyncio,rpc
Platform: all
Classifier: Programming Language :: Python
Classifier: Programming Language :: Python :: 3
Classifier: Programming Language :: Python :: 3.5
Classifier: Programming Language :: Python :: 3.6
Classifier: Programming Language :: Python :: 3.7
Classifier: Programming Language :: Python :: 3.8
Requires-Python: >3.5.*, <4
